persian_editor/__init__.py
persian_editor/apps.py
persian_editor/middleware.py
persian_editor/security.py
persian_editor/security_settings_example.py
persian_editor/urls.py
persian_editor/views.py
persian_editor/widgets.py
persian_editor/static/persian_editor/css/editor.css
persian_editor/static/persian_editor/js/editor.js
persian_editor/tests/__init__.py
persian_editor/tests/test_security.py
django_persian_editor-1.0.1.dist-info/LICENSE
django_persian_editor-1.0.1.dist-info/METADATA
django_persian_editor-1.0.1.dist-info/WHEEL
django_persian_editor-1.0.1.dist-info/top_level.txt
django_persian_editor-1.0.1.dist-info/RECORD
