Metadata-Version: 2.2
Name: django-persian-editor
Version: 1.0.1
Summary: یک ویرایشگر متن فارسی پیشرفته برای Django با پشتیبانی از RTL، حالت تاریک و امنیت بالا
Home-page: https://github.com/SaEeD802/django-persian-editor
Author: Persian Editor Team
Author-email: persianeditor.ir@gmail.com
License: MIT
Project-URL: Documentation, https://github.com/SaEeD802/django-persian-editor
Project-URL: Source, https://github.com/SaEeD802/django-persian-editor
Project-URL: Tracker, https://github.com/SaEeD802/django-persian-editor/issues
Project-URL: Changelog, https://github.com/SaEeD802/django-persian-editor/blob/main/CHANGELOG.md
Project-URL: Security, https://github.com/SaEeD802/django-persian-editor/blob/main/SECURITY.md
Keywords: django,editor,persian,rtl,wysiwyg,text,html,dark-mode,security
Classifier: Environment :: Web Environment
Classifier: Framework :: Django
Classifier: Framework :: Django :: 3.2
Classifier: Framework :: Django :: 4.0
Classifier: Framework :: Django :: 4.1
Classifier: Framework :: Django :: 4.2
Classifier: Framework :: Django :: 5.0
Classifier: Intended Audience :: Developers
Classifier: License :: OSI Approved :: MIT License
Classifier: Operating System :: OS Independent
Classifier: Programming Language :: Python
Classifier: Programming Language :: Python :: 3
Classifier: Programming Language :: Python :: 3.8
Classifier: Programming Language :: Python :: 3.9
Classifier: Programming Language :: Python :: 3.10
Classifier: Programming Language :: Python :: 3.11
Classifier: Programming Language :: Python :: 3.12
Classifier: Topic :: Internet :: WWW/HTTP
Classifier: Topic :: Internet :: WWW/HTTP :: Dynamic Content
Classifier: Topic :: Text Processing :: Markup :: HTML
Classifier: Natural Language :: Persian
Classifier: Development Status :: 5 - Production/Stable
Classifier: Intended Audience :: Developers
Classifier: Intended Audience :: Education
Requires-Python: >=3.8
License-File: LICENSE
Requires-Dist: Django>=3.2
Requires-Dist: bleach>=6.0.0
Requires-Dist: python-magic-bin>=0.4.14
Requires-Dist: tinycss2>=1.4.0
Dynamic: author
Dynamic: author-email
Dynamic: classifier
Dynamic: description
Dynamic: description-content-type
Dynamic: home-page
Dynamic: keywords
Dynamic: license
Dynamic: project-url
Dynamic: requires-dist
Dynamic: requires-python
Dynamic: summary
